php_framework_routes_to_openapi_converter/__init__.py
php_framework_routes_to_openapi_converter/cli.py
php_framework_routes_to_openapi_converter/core.py
php_framework_routes_to_openapi_converter/models.py
php_framework_routes_to_openapi_converter/converters/__init__.py
php_framework_routes_to_openapi_converter/converters/base.py
php_framework_routes_to_openapi_converter/converters/cakephp.py
php_framework_routes_to_openapi_converter/converters/codeigniter.py
php_framework_routes_to_openapi_converter/converters/drupal.py
php_framework_routes_to_openapi_converter/converters/drush.py
php_framework_routes_to_openapi_converter/converters/fastroute.py
php_framework_routes_to_openapi_converter/converters/fatfree.py
php_framework_routes_to_openapi_converter/converters/fuel.py
php_framework_routes_to_openapi_converter/converters/laminas.py
php_framework_routes_to_openapi_converter/converters/laravel.py
php_framework_routes_to_openapi_converter/converters/phalcon.py
php_framework_routes_to_openapi_converter/converters/phpixie.py
php_framework_routes_to_openapi_converter/converters/popphp.py
php_framework_routes_to_openapi_converter/converters/slim.py
php_framework_routes_to_openapi_converter/converters/symfony.py
php_framework_routes_to_openapi_converter/converters/thinkphp.py
php_framework_routes_to_openapi_converter/converters/yii.py
php_framework_routes_to_openapi_converter/converters/zendframework.py
php_framework_routes_to_openapi_converter/examples/__init__.py
php_framework_routes_to_openapi_converter/examples/codeigniter_example.py
php_framework_routes_to_openapi_converter/examples/example.py
php_framework_routes_to_openapi_converter/examples/laravel_example.py
php_framework_routes_to_openapi_converter/examples/symfony_example.py
php_framework_routes_to_openapi_converter/utils/__init__.py
php_framework_routes_to_openapi_converter/utils/parameter_analyzer.py
php_framework_routes_to_openapi_converter-0.1.8.dist-info/METADATA
php_framework_routes_to_openapi_converter-0.1.8.dist-info/WHEEL
php_framework_routes_to_openapi_converter-0.1.8.dist-info/entry_points.txt
php_framework_routes_to_openapi_converter-0.1.8.dist-info/top_level.txt
php_framework_routes_to_openapi_converter-0.1.8.dist-info/RECORD
