Metadata-Version: 2.4
Name: php-framework-routes-to-openapi-converter
Version: 0.1.8
Summary: Convert PHP framework routes to OpenAPI 3.0 specifications
Requires-Python: >=3.12
Requires-Dist: structlog>=25.4.0
Requires-Dist: typer>=0.16.0
